h0rton/__init__.py
h0rton/combine_lenses.py
h0rton/infer_h0_forward_modeling.py
h0rton/infer_h0_mcmc_default.py
h0rton/infer_h0_precision_ceiling.py
h0rton/infer_h0_simple_mc_truth.py
h0rton/infer_h0_tdlmc.py
h0rton/realize_time_delays.py
h0rton/script_utils.py
h0rton/summarize.py
h0rton/train.py
h0rton/train_Test.py
h0rton/configs/__init__.py
h0rton/configs/test_config.py
h0rton/configs/train_val_config.py
h0rton/h0_inference/__init__.py
h0rton/h0_inference/forward_modeling_posterior.py
h0rton/h0_inference/gaussian_bnn_posterior.py
h0rton/h0_inference/gaussian_bnn_posterior_cpu.py
h0rton/h0_inference/h0_posterior.py
h0rton/h0_inference/h0_utils.py
h0rton/h0_inference/mcmc_utils.py
h0rton/h0_inference/plotting_utils.py
h0rton/losses/__init__.py
h0rton/losses/gaussian_nll.py
h0rton/losses/gaussian_nll_cpu.py
h0rton/losses/gaussian_nll_native.py
h0rton/models/__init__.py
h0rton/models/bayesian_resnet.py
h0rton/tdlmc_data/__init__.py
h0rton/tdlmc_utils/__init__.py
h0rton/tdlmc_utils/reorder_images.py
h0rton/tdlmc_utils/tdlmc_metrics.py
h0rton/tdlmc_utils/tdlmc_parser.py
h0rton/tests/__init__.py
h0rton/tests/test_trainval_data/__init__.py
h0rton/tests/test_trainval_data/test_data_utils.py
h0rton/tests/test_trainval_data/test_xy_data.py
h0rton/train_utils/__init__.py
h0rton/train_utils/checkpoint_utils.py
h0rton/train_utils/logging_utils.py
h0rton/trainval_data/__init__.py
h0rton/trainval_data/data_utils.py
h0rton/trainval_data/tdlmc_data.py
h0rton/trainval_data/xy_data.py
h0rton-1.0.dist-info/LICENSE
h0rton-1.0.dist-info/METADATA
h0rton-1.0.dist-info/WHEEL
h0rton-1.0.dist-info/entry_points.txt
h0rton-1.0.dist-info/top_level.txt
h0rton-1.0.dist-info/RECORD
