Metadata-Version: 2.1
Name: h0rton
Version: 1.0
Summary: Bayesian neural network for hierarchical inference of the Hubble constant
Home-page: https://github.com/jiwoncpark/h0rton
Author: Ji Won Park
Author-email: jiwon.christine.park@gmail.com
License: LICENSE.md
Keywords: physics
Platform: UNKNOWN
Classifier: Development Status :: 4 - Beta
Classifier: License :: OSI Approved :: BSD License
Classifier: Intended Audience :: Developers
Classifier: Intended Audience :: Science/Research
Classifier: Operating System :: OS Independent
Classifier: Programming Language :: Python
